{
  "iterations": [
    {
      "iteration": 1,
      "startedAt": "2026-04-18T16:17:12.450Z",
      "endedAt": "2026-04-18T17:25:19.252Z",
      "durationMs": 3979558,
      "agent": "codex",
      "model": "",
      "toolsUsed": {
        "exec_command": 1,
        "a": 4,
        "on": 3,
        "grep": 3,
        "Playwright": 1,
        "UTC": 3,
        "the": 3,
        "confusion": 1,
        "Vitest": 1,
        "it": 1,
        "end-to-end": 1,
        "dynamic": 2
      },
      "filesModified": [
        ".ralph/ralph-decision-log.md",
        ".ralph/ralph-tasks.md",
        "src/pages/champion-detail/detail-derived-sections.ts",
        "src/pages/champion-detail/detail-localization.ts",
        "src/pages/champion-detail/detail-value-formatters.ts",
        "src/pages/champion-detail/summary-model.ts",
        "tests/component/championDetailPage.content.test.tsx",
        "tests/unit/champion-detail/detail-value-formatters.test.ts",
        "tests/unit/champion-detail/summary-model.test.ts"
      ],
      "exitCode": 0,
      "completionDetected": false,
      "errors": [
        "I'm handling a new unit test for the filter, and we might not need to change the component fixture. The component test needs an update to check for the absence of the shop/timegate label, especially i",
        "Error: EPERM: operation not permitted, mkdir '/Users/rain/Library/Caches/ms-playwright'",
        "[Error: 00A6740801000000:error:0A0001BB:SSL routines:tls13_validate_record_header:bad record type:ssl/record/methods/tls13_meth.c:258:"
      ]
    },
    {
      "iteration": 2,
      "startedAt": "2026-04-18T17:27:08.029Z",
      "endedAt": "2026-04-18T17:57:03.673Z",
      "durationMs": 1688522,
      "agent": "codex",
      "model": "",
      "toolsUsed": {
        "1": 1,
        "parallel": 1,
        "the": 3,
        "custom": 1,
        "on": 1,
        "a": 1,
        "dynamic": 2,
        "this": 1,
        "smoke": 1,
        "one": 1,
        "those": 1
      },
      "filesModified": [
        ".gitignore",
        ".ralph/ralph-decision-log.md",
        ".ralph/ralph-tasks.md",
        "src/app/App.tsx",
        "src/app/LocaleSwitcher.tsx",
        "src/app/PrimaryNavigation.tsx",
        "src/app/SiteHeader.tsx",
        "src/app/appNavigation.ts",
        "src/pages/champions/ChampionResultCard.tsx",
        "src/pages/illustrations/IllustrationResultCard.tsx",
        "src/styles/app/navigation.css",
        "src/styles/app/shell.css",
        "src/styles/app/site-header.css",
        "tests/component/app.test.tsx",
        "tests/component/primaryNavigation.test.tsx",
        "tests/e2e/header-condense-layout.spec.ts"
      ],
      "exitCode": 0,
      "completionDetected": false,
      "errors": [
        "❯ |component| tests/component/primaryNavigation.test.tsx (3 tests | 1 failed) 304ms",
        "⎯⎯⎯⎯⎯⎯⎯ Failed Tests 1 ⎯⎯⎯⎯⎯⎯⎯",
        "FAIL  |component| tests/component/primaryNavigation.test.tsx > PrimaryNavigation > 从立绘图鉴进入英雄详情时保持立绘图鉴导航高亮",
        "Error: expect(element).toHaveAttribute(\"aria-current\", \"page\") // element.getAttribute(\"aria-current\") === \"page\"",
        "Error: EPERM: operation not permitted, mkdir '/Users/rain/Library/Caches/ms-playwright'",
        "[Error: 0066AF1E01000000:error:0A000119:SSL routines:tls_get_more_records:decryption failed or bad record mac:ssl/record/methods/tls_common.c:870:",
        "Error: browserType.launch: Target page, context or browser has been closed",
        "[pid=43075][err] [0419/015030.260060:ERROR:base/power_monitor/thermal_state_observer_mac.mm:140] ThermalStateObserverMac unable to register to power notifications. Result: 9",
        "\u001b[2m  - [pid=43075][err] [0419/015030.260060:ERROR:base/power_monitor/thermal_state_observer_mac.mm:140] ThermalStateObserverMac unable to register to power notifications. Result: 9\u001b[22m"
      ]
    },
    {
      "iteration": 3,
      "startedAt": "2026-04-18T17:58:51.958Z",
      "endedAt": "2026-04-18T18:17:54.628Z",
      "durationMs": 1035561,
      "agent": "codex",
      "model": "",
      "toolsUsed": {
        "into": 2,
        "the": 3,
        "grep": 1,
        "Playwright": 2,
        "Node": 1,
        "a": 4,
        "React": 1,
        "layout": 1,
        "jsdom": 1,
        "on": 2,
        "any": 1,
        "compile": 1,
        "dynamic": 2
      },
      "filesModified": [
        ".ralph/ralph-decision-log.md",
        ".ralph/ralph-tasks.md",
        "src/components/PageTabHeader.tsx",
        "src/pages/ChampionsPage.tsx",
        "src/pages/IllustrationsPage.tsx",
        "src/pages/PetsPage.tsx",
        "src/pages/PresetsPage.tsx",
        "src/pages/VariantsPage.tsx",
        "src/pages/formation/FormationEditorCard.tsx",
        "src/pages/user-data/UserDataIntroCard.tsx",
        "src/styles/shared/surfaces.css",
        "tests/component/pageTabHeader.test.tsx"
      ],
      "exitCode": 0,
      "completionDetected": false,
      "errors": [
        "Error: EPERM: operation not permitted, mkdir '/Users/rain/Library/Caches/ms-playwright'",
        "[pid=56904][err] [0419/020328.694384:ERROR:base/power_monitor/thermal_state_observer_mac.mm:140] ThermalStateObserverMac unable to register to power notifications. Result: 9",
        "\u001b[2m  - [pid=56904][err] [0419/020328.694384:ERROR:base/power_monitor/thermal_state_observer_mac.mm:140] ThermalStateObserverMac unable to register to power notifications. Result: 9\u001b[22m",
        "\u001b[2m  - [pid=56904] exception while trying to kill process: Error: kill ESRCH\u001b[22m",
        "❯ |component| tests/component/pageTabHeader.test.tsx (1 test | 1 failed) 30ms",
        "⎯⎯⎯⎯⎯⎯⎯ Failed Tests 1 ⎯⎯⎯⎯⎯⎯⎯",
        "FAIL  |component| tests/component/pageTabHeader.test.tsx > PageTabHeader > 把公共数据元信息并到首行，并且不再渲染副标题",
        "Error: expect(received).toBeInTheDocument()",
        "I need to think about removing the CSS description and checking for any property errors. Should I patch the test to remove the description property? But actually, the test uses the description propert"
      ]
    }
  ],
  "totalDurationMs": 6703641,
  "struggleIndicators": {
    "repeatedErrors": {
      "I'm handling a new unit test for the filter, and we might not need to change the component fixture. ": 1,
      "Error: EPERM: operation not permitted, mkdir '/Users/rain/Library/Caches/ms-playwright'": 3,
      "[Error: 00A6740801000000:error:0A0001BB:SSL routines:tls13_validate_record_header:bad record type:ss": 1,
      "❯ |component| tests/component/primaryNavigation.test.tsx (3 tests | 1 failed) 304ms": 1,
      "⎯⎯⎯⎯⎯⎯⎯ Failed Tests 1 ⎯⎯⎯⎯⎯⎯⎯": 2,
      "FAIL  |component| tests/component/primaryNavigation.test.tsx > PrimaryNavigation > 从立绘图鉴进入英雄详情时保持立绘图": 1,
      "Error: expect(element).toHaveAttribute(\"aria-current\", \"page\") // element.getAttribute(\"aria-current": 1,
      "[Error: 0066AF1E01000000:error:0A000119:SSL routines:tls_get_more_records:decryption failed or bad r": 1,
      "Error: browserType.launch: Target page, context or browser has been closed": 1,
      "[pid=43075][err] [0419/015030.260060:ERROR:base/power_monitor/thermal_state_observer_mac.mm:140] The": 1,
      "\u001b[2m  - [pid=43075][err] [0419/015030.260060:ERROR:base/power_monitor/thermal_state_observer_mac.mm:": 1,
      "[pid=56904][err] [0419/020328.694384:ERROR:base/power_monitor/thermal_state_observer_mac.mm:140] The": 1,
      "\u001b[2m  - [pid=56904][err] [0419/020328.694384:ERROR:base/power_monitor/thermal_state_observer_mac.mm:": 1,
      "\u001b[2m  - [pid=56904] exception while trying to kill process: Error: kill ESRCH\u001b[22m": 1,
      "❯ |component| tests/component/pageTabHeader.test.tsx (1 test | 1 failed) 30ms": 1,
      "FAIL  |component| tests/component/pageTabHeader.test.tsx > PageTabHeader > 把公共数据元信息并到首行，并且不再渲染副标题": 1,
      "Error: expect(received).toBeInTheDocument()": 1,
      "I need to think about removing the CSS description and checking for any property errors. Should I pa": 1
    },
    "noProgressIterations": 0,
    "shortIterations": 0
  }
}